README.txt
krypto.py
setup.py
krypto.egg-info/PKG-INFO
krypto.egg-info/SOURCES.txt
krypto.egg-info/dependency_links.txt
krypto.egg-info/entry_points.txt
krypto.egg-info/requires.txt
krypto.egg-info/top_level.txt