Metadata-Version: 1.1
Name: krypto
Version: 9.3.0
Summary: encrypt files and data
Home-page: https://github.com/techiekrish
Author: krish
Author-email: krishgarg19@gmail.com
License:  
Platform: UNKNOWN
Classifier: Development Status :: 3 - Alpha
Classifier: Intended Audience :: Developers
Classifier: Programming Language :: Python :: 3.7
